nethack_neural/__init__.py
nethack_neural/main.py
nethack_neural/agents/__init__.py
nethack_neural/agents/abstract_agent.py
nethack_neural/agents/ppo_agent.py
nethack_neural/agents/random_agent.py
nethack_neural/buffers/__init__.py
nethack_neural/buffers/abstract_buffer.py
nethack_neural/buffers/rollout_buffer.py
nethack_neural/loggers/__init__.py
nethack_neural/loggers/abstract_logger.py
nethack_neural/loggers/file_logger.py
nethack_neural/loggers/stdout_logger.py
nethack_neural/networks/__init__.py
nethack_neural/networks/input_heads.py
nethack_neural/runners/__init__.py
nethack_neural/runners/abstract_runner.py
nethack_neural/runners/default_runner.py
nethack_neural/runners/ppo_full_runner.py
nethack_neural/utils/__init__.py
nethack_neural/utils/env_specs.py
nethack_neural/utils/transition.py
nethack_neural-0.6.dist-info/METADATA
nethack_neural-0.6.dist-info/WHEEL
nethack_neural-0.6.dist-info/entry_points.txt
nethack_neural-0.6.dist-info/top_level.txt
nethack_neural-0.6.dist-info/RECORD
